pyjection/__init__.py
pyjection/dependency_injector.py
pyjection/helper.py
pyjection/reference.py
pyjection/service.py
pyjection-1.0.0.dist-info/DESCRIPTION.rst
pyjection-1.0.0.dist-info/METADATA
pyjection-1.0.0.dist-info/RECORD
pyjection-1.0.0.dist-info/WHEEL
pyjection-1.0.0.dist-info/metadata.json
pyjection-1.0.0.dist-info/top_level.txt
