Metadata-Version: 2.0
Name: pyjection
Version: 1.0.0
Summary: Pyjection is a lightweight python dependency injection library
Home-page: https://github.com/Darkheir/pyjection
Author: Raphael Cohen
Author-email: raphael.cohen.utt@gmail.com
License: MIT
Keywords: dependency injection dependency-injection development
Platform: UNKNOWN
Classifier: Development Status :: 4 - Beta
Classifier: Operating System :: OS Independent
Classifier: Intended Audience :: Developers
Classifier: Topic :: Software Development :: Libraries :: Python Modules
Classifier: License :: OSI Approved :: MIT License
Classifier: Programming Language :: Python :: 3
Classifier: Programming Language :: Python :: 3.3
Classifier: Programming Language :: Python :: 3.4
Classifier: Natural Language :: English
Provides-Extra: test
Requires-Dist: coverage; extra == 'test'
